{
    "products":[
        {
            "id": 1,
            "name": "Monkey D. Luffy",
            "desc": "KING OF THE PIRATES",
            "price": 999,
           " color": "#ed1111",
            "image":"https://cdn.shopify.com/s/files/1/0261/5433/6341/products/WhatsAppImage2022-01-28at3.02.33PM_360x.jpg?v=1680685778"
        },

        {
            "id": 2,
            "name": "Roronoa Zoro",
            "desc": "KING OF Hell",
            "price": 899,
            "color": "#55cc2d",
            "image":"https://cdn.shopify.com/s/files/1/0261/5433/6341/products/1_5390c81d-6665-4a9e-8b9f-dc69fdd8d886_360x.jpg?v=1654517894"
        },
        {
            "id": 3,
            "name": "Vinsmoke Sanji",
            "desc": "Black Foot",
            "price": 899,
            "color": "#e6e212",
            "image":"https://cdn.shopify.com/s/files/1/0261/5433/6341/files/517N6621OdL._AC_UL400_-removebg-preview_360x.png?v=1684231667"
        },
        {
            "id":4,
            "name": "Nami",
            "desc": "Cat Burglar Nami",
            "price": 799,
            "color": "#f58122",
            "image":"https://cdn.shopify.com/s/files/1/0261/5433/6341/products/WhatsAppImage2022-06-06at6.10.28PM_2_360x.jpg?v=1654519326"
        },
        {
            "id": 5,
            "name": "Nico Robin",
            "desc": "Devil Child",
            "price": 799,
            "color": "#9915e6",
            "image":"https://cdn.shopify.com/s/files/1/0261/5433/6341/files/873a8143-6006-4c44-9e1b-66c3108a3ed2_360x.jpg?v=1688368745"
            
        },
        {
            "id": 6,
            "name": "Usopp",
            "desc": "God Usopp",
            "price": 799,
            "color": "#f58122",
            "image":"https://cdn.shopify.com/s/files/1/0261/5433/6341/files/d615e3b6-2ac4-4743-9397-b0cf41a604bd_360x.jpg?v=1688366313"
            
        },
        {
            "id": 7,
            "name": "Tony Tony Chopper",
            "desc": "Cotton Candy Lover",
            "price": 699,
            "color": "#eb7ce1",
            "image":"https://cdn.shopify.com/s/files/1/0261/5433/6341/files/abfe7163-1367-48c5-b06a-e08aec6a87c1_360x.jpg?v=1688366468"
            
        },
        {
            "id": 8,
            "name": "Franky",
            "desc": "Cyborg",
            "price": 799,
            "color": "#24d4d4",
            "image":"https://cdn.shopify.com/s/files/1/0261/5433/6341/files/20230705_115834_360x.jpg?v=1688549786"
            
        },
        {
            "id": 9,
            "name": "Brook",
            "desc": "Soul King",
            "price": 799,
            "color": "#140013",
            "image":"https://encrypted-tbn0.gstatic.com/images?q=tbn:ANd9GcSlznQ56penyC03P7t9Hyts_jpatTk0Eb3kqw&usqp=CAU"
            
        },
        
        {
            "id": 10,
            "name": "Jinbe",
            "desc": "First Son of the Sea",
            "price": 799,
            "color": "#50e6fa",
            "image":"https://encrypted-tbn0.gstatic.com/images?q=tbn:ANd9GcQrJLB8me_R8QO67NhgrCtxIJeprzRURQ2QjQ&usqp=CAU"
            
        }

    ]
}